<?xml version="1.0" encoding="UTF-8" standalone="no"?>
<!DOCTYPE tiles-definitions PUBLIC "-//Apache Software Foundation//DTD Tiles Configuration 2.1//EN" "http://tiles.apache.org/dtds/tiles-config_2_1.dtd">
<tiles-definitions>
    <definition extends="default" name="userlogins/create">
        <put-attribute name="body" value="/WEB-INF/views/userlogins/create.jspx"/>
    </definition>
    
    <definition extends="default" name="userlogins/edit">
        <put-attribute name="body" value="/WEB-INF/views/userlogins/edit.jspx"/>
    </definition>
        
    <definition extends="default" name="userlogins/list">
        <put-attribute name="body" value="/WEB-INF/views/userlogins/list.jspx"/>
    </definition>
    
   
</tiles-definitions>
